FermiSoftness/__init__.py
FermiSoftness/gen.py
FermiSoftness/cp2k/__init__.py
FermiSoftness/cp2k/cp2k.py
FermiSoftness/qe/__init__.py
FermiSoftness/qe/qe.py
FermiSoftness/vasp/__init__.py
FermiSoftness/vasp/vasp.py
FermiSoftness-1.2.0.1.dist-info/LICENSE
FermiSoftness-1.2.0.1.dist-info/METADATA
FermiSoftness-1.2.0.1.dist-info/WHEEL
FermiSoftness-1.2.0.1.dist-info/entry_points.txt
FermiSoftness-1.2.0.1.dist-info/top_level.txt
FermiSoftness-1.2.0.1.dist-info/RECORD
